clickcounter/__init__.py
clickcounter/_cli.py
clickcounter/_utils.py
clickcounter/providers/__init__.py
clickcounter/providers/_base.py
clickcounter/providers/linkclickcounter_com.py
clickcounter/providers/shorturl_at.py
clickcounter-1.0.4.dist-info/entry_points.txt
clickcounter-1.0.4.dist-info/LICENSE
clickcounter-1.0.4.dist-info/WHEEL
clickcounter-1.0.4.dist-info/METADATA
clickcounter-1.0.4.dist-info/RECORD
