Metadata-Version: 2.1
Name: clickcounter
Version: 1.0.4
Summary: Create redirect url's with click monitoring from multiple providers
License: MIT
Author: Johannes Valbjorn
Author-email: johannes.valbjorn@gmail.com
Requires-Python: >=3.8,<4.0
Classifier: License :: OSI Approved :: MIT License
Classifier: Programming Language :: Python :: 3
Classifier: Programming Language :: Python :: 3.8
Classifier: Programming Language :: Python :: 3.9
Requires-Dist: lxml (>=4.6.3,<5.0.0)
Requires-Dist: requests (>=2.25.1,<3.0.0)
